odoo/addons/stock_location_bin_name/README.rst
odoo/addons/stock_location_bin_name/__init__.py
odoo/addons/stock_location_bin_name/__manifest__.py
odoo/addons/stock_location_bin_name/i18n/it.po
odoo/addons/stock_location_bin_name/i18n/stock_location_bin_name.pot
odoo/addons/stock_location_bin_name/models/__init__.py
odoo/addons/stock_location_bin_name/models/stock_location.py
odoo/addons/stock_location_bin_name/readme/CONTRIBUTORS.md
odoo/addons/stock_location_bin_name/readme/CREDITS.md
odoo/addons/stock_location_bin_name/readme/DESCRIPTION.md
odoo/addons/stock_location_bin_name/static/description/icon.png
odoo/addons/stock_location_bin_name/static/description/index.html
odoo/addons/stock_location_bin_name/tests/__init__.py
odoo/addons/stock_location_bin_name/tests/test_stock_location_bin_name.py
odoo/addons/stock_location_bin_name/tests/test_stock_location_formatter.py
odoo/addons/stock_location_bin_name/views/stock_location.xml
odoo_addon_stock_location_bin_name-18.0.1.0.1.1.dist-info/METADATA
odoo_addon_stock_location_bin_name-18.0.1.0.1.1.dist-info/WHEEL
odoo_addon_stock_location_bin_name-18.0.1.0.1.1.dist-info/top_level.txt
odoo_addon_stock_location_bin_name-18.0.1.0.1.1.dist-info/RECORD
