Metadata-Version: 2.1
Name: odoo-addon-stock_location_bin_name
Version: 18.0.1.0.1.1
Requires-Python: >=3.10
Requires-Dist: odoo-addon-stock_location_position==18.0.*
Requires-Dist: odoo-addon-stock_location_zone==18.0.*
Requires-Dist: odoo==18.0.*
Summary: Compute bin stock location name automatically
Home-page: https://github.com/OCA/stock-logistics-warehouse
License: AGPL-3
Author: BCIM, Okia, Camptocamp, Odoo Community Association (OCA)
Author-email: support@odoo-community.org
Classifier: Programming Language :: Python
Classifier: Framework :: Odoo
Classifier: Framework :: Odoo :: 18.0
Classifier: License :: OSI Approved :: GNU Affero General Public License v3
Classifier: Development Status :: 3 - Alpha
